{
  "project_info": {
    "project_number": "383291232276",
    "project_id": "tammy-57449",
    "storage_bucket": "tammy-57449.appspot.com"
  },
  "client": [
    {
      "client_info": {
        "mobilesdk_app_id": "1:383291232276:android:0190af0d6f60206b221701",
        "android_client_info": {
          "package_name": "com.zendev.telecrypt"
        }
      },
      "oauth_client": [],
      "api_key": [
        {
          "current_key": "AIzaSyDhv6zW2beEf3sJGpWBN6QQBx3f958u2Y8"
        }
      ],
      "services": {
        "appinvite_service": {
          "other_platform_oauth_client": []
        }
      }
    },
    {
      "client_info": {
        "mobilesdk_app_id": "1:383291232276:android:161d04f2c171a80d221701",
        "android_client_info": {
          "package_name": "com.zendev.telecrypt.dev"
        }
      },
      "oauth_client": [],
      "api_key": [
        {
          "current_key": "AIzaSyDhv6zW2beEf3sJGpWBN6QQBx3f958u2Y8"
        }
      ],
      "services": {
        "appinvite_service": {
          "other_platform_oauth_client": []
        }
      }
    }
  ],
  "configuration_version": "1"
}
